DFPlayer/DFPlayer.py
DFPlayer/__init__.py
DFPlayer-0.1.2.dist-info/LICENSE
DFPlayer-0.1.2.dist-info/METADATA
DFPlayer-0.1.2.dist-info/WHEEL
DFPlayer-0.1.2.dist-info/top_level.txt
DFPlayer-0.1.2.dist-info/RECORD
