Metadata-Version: 2.1
Name: DFPlayer
Version: 0.1.2
Summary: Python3 library for the DFPlayer-mini
Home-page: https://github.com/dianudi/dfplayer-py
Author: Dianudi
Author-email: dianudi <dian_udi@proton.me>
License: MIT License
Project-URL: Homepage, https://github.com/dianudi/dfplayer-py
Project-URL: Issues, https://github.com/dianudi/dfplayer-py/issues
Keywords: dfplayer,dfplayer-mini,mp3-module
Classifier: Programming Language :: Python :: 3
Classifier: License :: OSI Approved :: MIT License
Classifier: Operating System :: OS Independent
Requires: pyserial
Requires-Python: >=3.8
License-File: LICENSE
Requires-Dist: pyserial
